LICENSE.txt
setup.cfg
setup.py
Prob15/__init__.py
Prob15/code.py
Prob15.egg-info/PKG-INFO
Prob15.egg-info/SOURCES.txt
Prob15.egg-info/dependency_links.txt
Prob15.egg-info/not-zip-safe
Prob15.egg-info/top_level.txt